{

    "Basic": {
        "ru": [
            "Как вас зовут? (ФИО)", 
            "Сколько вам лет?",
            "Ваш рабочий номер телефона?",
            "Какого ваше образование?",
            "Чем вы увлекаетесь?"
        ],
        "uzb": [
            "Как вас зовут? (ФИО)", 
            "Сколько вам лет?",
            "Ваш рабочий номер телефона?",
            "Какого ваше образование?",
            "Чем вы увлекаетесь?"
        ]
    },

    "Asia Cons": {
        "ru": [
            "Какие перспективы вами движут?",
            "На сколько вы амбициозны?",
            "Вы готовы работать уже на следующий день?"
        ],
        "uzb": [
            "Какие перспективы вами движут?",
            "На сколько вы амбициозны?",
            "Вы готовы работать уже на следующий день?"
        ]
    },

    "Movaroun": {
        "ru": [
            "Умеешь жарить мясо?"
        ],  
        "uzb": [
            "Умеешь жарить мясо?"
        ]
    },

    "Oila Market": {
        "ru": [
            "Как вы ладите с людьми?"
        ],
        "uzb": [
            "Как вы ладите с людьми?"
        ]   
    }

}